quantum_sdk/__init__.py
quantum_sdk/core.py
quantum_scoring_sdk-0.3.4.dist-info/METADATA
quantum_scoring_sdk-0.3.4.dist-info/WHEEL
quantum_scoring_sdk-0.3.4.dist-info/top_level.txt
quantum_scoring_sdk-0.3.4.dist-info/RECORD
