Metadata-Version: 2.4
Name: quantum-scoring-sdk
Version: 0.3.4
Summary: Quantum-native framework with IBM Quantum hardware support and enterprise license control
Author: Jaime Alexander Jimenez Lozano
Author-email: jaimeajl@hotmail.com
Classifier: Programming Language :: Python :: 3
Classifier: License :: Other/Proprietary License
Classifier: Operating System :: OS Independent
Classifier: Development Status :: 4 - Beta
Classifier: Topic :: Scientific/Engineering :: Physics
Requires-Python: >=3.8
Requires-Dist: numpy
Requires-Dist: scikit-learn
Requires-Dist: qiskit>=0.45.0
Requires-Dist: qiskit-aer>=0.13.0
Requires-Dist: requests
Provides-Extra: ibm
Requires-Dist: qiskit-ibm-runtime>=0.15.0; extra == "ibm"
Dynamic: author
Dynamic: author-email
Dynamic: classifier
Dynamic: description
Dynamic: description-content-type
Dynamic: provides-extra
Dynamic: requires-dist
Dynamic: requires-python
Dynamic: summary
